{
  "indexes": [
    {
      "collectionGroup": "avis",
      "queryScope": "COLLECTION_GROUP",
      "fields": [
        { "fieldPath": "visible", "order": "ASCENDING" },
        { "fieldPath": "createdAt", "order": "DESCENDING" }
      ]
    },
    {
      "collectionId": "tripCosts",
      "queryScope": "COLLECTION",
      "fields": [
        { "fieldPath": "date", "order": "ASCENDING" },
        { "fieldPath": "createdAt", "order": "DESCENDING" }
      ]
    },
    {
      "collectionId": "tripCosts",
      "queryScope": "COLLECTION",
      "fields": [
        { "fieldPath": "agencyId", "order": "ASCENDING" },
        { "fieldPath": "createdAt", "order": "DESCENDING" }
      ]
    },
    {
      "collectionId": "tripCosts",
      "queryScope": "COLLECTION",
      "fields": [
        { "fieldPath": "date", "order": "ASCENDING" },
        { "fieldPath": "agencyId", "order": "ASCENDING" },
        { "fieldPath": "createdAt", "order": "DESCENDING" }
      ]
    },
    {
      "collectionGroup": "reservations",
      "queryScope": "COLLECTION",
      "fields": [
        { "fieldPath": "agencyId", "order": "ASCENDING" },
        { "fieldPath": "createdAt", "order": "ASCENDING" },
        { "fieldPath": "statut", "order": "ASCENDING" }
      ]
    },
    {
      "collectionGroup": "reservations",
      "queryScope": "COLLECTION",
      "fields": [
        { "fieldPath": "companyId", "order": "ASCENDING" },
        { "fieldPath": "createdAt", "order": "DESCENDING" }
      ]
    },
    {
      "collectionGroup": "dailyStats",
      "queryScope": "COLLECTION_GROUP",
      "fields": [
        { "fieldPath": "companyId", "order": "ASCENDING" },
        { "fieldPath": "date", "order": "ASCENDING" }
      ]
    },
    {
      "collectionGroup": "agencyLiveState",
      "queryScope": "COLLECTION_GROUP",
      "fields": [
        { "fieldPath": "companyId", "order": "ASCENDING" }
      ]
    },
    {
      "collectionGroup": "shiftReports",
      "queryScope": "COLLECTION_GROUP",
      "fields": [
        { "fieldPath": "companyId", "order": "ASCENDING" },
        { "fieldPath": "status", "order": "ASCENDING" }
      ]
    },
    {
      "collectionGroup": "shifts",
      "queryScope": "COLLECTION_GROUP",
      "fields": [
        { "fieldPath": "companyId", "order": "ASCENDING" },
        { "fieldPath": "status", "order": "ASCENDING" }
      ]
    },
    {
      "collectionGroup": "shifts",
      "queryScope": "COLLECTION_GROUP",
      "fields": [
        { "fieldPath": "compagnieId", "order": "ASCENDING" },
        { "fieldPath": "status", "order": "ASCENDING" }
      ]
    },
    {
      "collectionGroup": "reservations",
      "queryScope": "COLLECTION_GROUP",
      "fields": [
        { "fieldPath": "companyId", "order": "ASCENDING" },
        { "fieldPath": "date", "order": "ASCENDING" }
      ]
    },
    {
      "collectionGroup": "reservations",
      "queryScope": "COLLECTION_GROUP",
      "fields": [
        { "fieldPath": "compagnieId", "order": "ASCENDING" },
        { "fieldPath": "date", "order": "ASCENDING" }
      ]
    },
    {
      "collectionGroup": "reservations",
      "queryScope": "COLLECTION_GROUP",
      "fields": [
        { "fieldPath": "companyId", "order": "ASCENDING" },
        { "fieldPath": "createdAt", "order": "ASCENDING" }
      ]
    },
    {
      "collectionGroup": "reservations",
      "queryScope": "COLLECTION_GROUP",
      "fields": [
        { "fieldPath": "compagnieId", "order": "ASCENDING" },
        { "fieldPath": "createdAt", "order": "ASCENDING" }
      ]
    },
    {
      "collectionGroup": "dailyTrips",
      "queryScope": "COLLECTION",
      "fields": [
        { "fieldPath": "agencyId", "order": "ASCENDING" },
        { "fieldPath": "departure", "order": "ASCENDING" },
        { "fieldPath": "arrival", "order": "ASCENDING" },
        { "fieldPath": "date", "order": "ASCENDING" },
        { "fieldPath": "time", "order": "ASCENDING" }
      ]
    },

    
    {
      "collectionId": "companies",
      "queryScope": "COLLECTION",
      "fields": [
        { "fieldPath": "publicPageEnabled", "order": "ASCENDING" },
        { "fieldPath": "updatedAt", "order": "DESCENDING" }
      ]
    },
    {
      "collectionId": "companies",
      "queryScope": "COLLECTION",
      "fields": [
        { "fieldPath": "publicPageEnabled", "order": "ASCENDING" },
        { "fieldPath": "status", "order": "ASCENDING" },
        { "fieldPath": "updatedAt", "order": "DESCENDING" }
      ]
    },
    {
      "collectionId": "companies",
      "queryScope": "COLLECTION",
      "fields": [
        { "fieldPath": "publicPageEnabled", "order": "ASCENDING" },
        { "fieldPath": "pays", "order": "ASCENDING" },
        { "fieldPath": "updatedAt", "order": "DESCENDING" }
      ]
    },
    {
      "collectionGroup": "financialMovements",
      "queryScope": "COLLECTION_GROUP",
      "fields": [
        { "fieldPath": "performedAt", "order": "DESCENDING" }
      ]
    },
    {
      "collectionGroup": "financialMovements",
      "queryScope": "COLLECTION_GROUP",
      "fields": [
        { "fieldPath": "agencyId", "order": "ASCENDING" },
        { "fieldPath": "performedAt", "order": "DESCENDING" }
      ]
    },
    {
      "collectionGroup": "financialMovements",
      "queryScope": "COLLECTION_GROUP",
      "fields": [
        { "fieldPath": "fromAccountId", "order": "ASCENDING" },
        { "fieldPath": "performedAt", "order": "DESCENDING" }
      ]
    },
    {
      "collectionGroup": "financialMovements",
      "queryScope": "COLLECTION_GROUP",
      "fields": [
        { "fieldPath": "toAccountId", "order": "ASCENDING" },
        { "fieldPath": "performedAt", "order": "DESCENDING" }
      ]
    },
    {
      "collectionGroup": "financialAccounts",
      "queryScope": "COLLECTION_GROUP",
      "fields": [
        { "fieldPath": "isActive", "order": "ASCENDING" },
        { "fieldPath": "agencyId", "order": "ASCENDING" }
      ]
    },
    {
      "collectionGroup": "expenses",
      "queryScope": "COLLECTION_GROUP",
      "fields": [
        { "fieldPath": "status", "order": "ASCENDING" },
        { "fieldPath": "createdAt", "order": "DESCENDING" }
      ]
    },
    {
      "collectionGroup": "expenses",
      "queryScope": "COLLECTION_GROUP",
      "fields": [
        { "fieldPath": "agencyId", "order": "ASCENDING" },
        { "fieldPath": "status", "order": "ASCENDING" }
      ]
    },
    {
      "collectionId": "payables",
      "queryScope": "COLLECTION",
      "fields": [
        { "fieldPath": "agencyId", "order": "ASCENDING" },
        { "fieldPath": "createdAt", "order": "DESCENDING" }
      ]
    },
    {
      "collectionId": "payables",
      "queryScope": "COLLECTION",
      "fields": [
        { "fieldPath": "status", "order": "ASCENDING" },
        { "fieldPath": "createdAt", "order": "DESCENDING" }
      ]
    },
    {
      "collectionId": "fleetMaintenance",
      "queryScope": "COLLECTION",
      "fields": [
        { "fieldPath": "agencyId", "order": "ASCENDING" },
        { "fieldPath": "createdAt", "order": "DESCENDING" }
      ]
    },
    {
      "collectionId": "fleetMaintenance",
      "queryScope": "COLLECTION",
      "fields": [
        { "fieldPath": "vehicleId", "order": "ASCENDING" },
        { "fieldPath": "createdAt", "order": "DESCENDING" }
      ]
    },
    {
      "collectionGroup": "paymentProposals",
      "queryScope": "COLLECTION_GROUP",
      "fields": [
        { "fieldPath": "approvalStatus", "order": "ASCENDING" },
        { "fieldPath": "proposedAt", "order": "DESCENDING" }
      ]
    },
    {
      "collectionGroup": "paymentProposals",
      "queryScope": "COLLECTION_GROUP",
      "fields": [
        { "fieldPath": "payableId", "order": "ASCENDING" },
        { "fieldPath": "proposedAt", "order": "ASCENDING" },
        { "fieldPath": "approvalStatus", "order": "ASCENDING" }
      ]
    },
    {
      "collectionGroup": "courierSessions",
      "queryScope": "COLLECTION_GROUP",
      "fields": [
        { "fieldPath": "agentId", "order": "ASCENDING" }
      ]
    },
    {
      "collectionGroup": "shipments",
      "queryScope": "COLLECTION_GROUP",
      "fields": [
        { "fieldPath": "sessionId", "order": "ASCENDING" }
      ]
    },
    {
      "collectionGroup": "shipments",
      "queryScope": "COLLECTION_GROUP",
      "fields": [
        { "fieldPath": "destinationAgencyId", "order": "ASCENDING" },
        { "fieldPath": "currentStatus", "order": "ASCENDING" }
      ]
    },
    {
      "collectionGroup": "shipments",
      "queryScope": "COLLECTION_GROUP",
      "fields": [
        { "fieldPath": "receiver.phone", "order": "ASCENDING" },
        { "fieldPath": "currentAgencyId", "order": "ASCENDING" },
        { "fieldPath": "currentStatus", "order": "ASCENDING" }
      ]
    },
    {
      "collectionGroup": "shipments",
      "queryScope": "COLLECTION_GROUP",
      "fields": [
        { "fieldPath": "originAgencyId", "order": "ASCENDING" }
      ]
    }
  ],
  "fieldOverrides": []
}
